SFLvault_client-0.9.2-py3.8-nspkg.pth
sflvault/client/__init__.py
sflvault/client/client.py
sflvault/client/commands.py
sflvault/client/fallback.py
sflvault/client/fishlib.py
sflvault/client/remoting.py
sflvault/client/services.py
sflvault/client/ui.py
sflvault/client/utils.py
sflvault/plugins/__init__.py
SFLvault_client-0.9.2.dist-info/.gitignore
SFLvault_client-0.9.2.dist-info/METADATA
SFLvault_client-0.9.2.dist-info/WHEEL
SFLvault_client-0.9.2.dist-info/entry_points.txt
SFLvault_client-0.9.2.dist-info/namespace_packages.txt
SFLvault_client-0.9.2.dist-info/top_level.txt
SFLvault_client-0.9.2.dist-info/RECORD
